[
    {
        "locationName": "Europe",
        "locationUrl": "/europe",
        "locationType": "CONTINENT",
        "locationChildren": [
            {
                "locationName": "Italy",
                "locationUrl": "/europe/italy",
                "locationType": "COUNTRY",
                "locationChildren": [
                    {
                        "locationName": "Rome",
                        "locationUrl": "/europe/italy/rome",
                        "locationType": "CITY"
                    },
                    {
                        "locationName": "Milan",
                        "locationUrl": "/europe/italy/milan",
                        "locationType": "CITY"
                    }
                ]
            },
            {
                "locationName": "France",
                "locationUrl": "/europe/france",
                "locationType": "COUNTRY",
                "locationChildren": [
                    {
                        "locationName": "Rome",
                        "locationUrl": "/europe/france/paris",
                        "locationType": "CITY"
                    },
                    {
                        "locationName": "Milan",
                        "locationUrl": "/europe/france/lyon",
                        "locationType": "CITY"
                    }
                ]
            },
            {
                "locationName": "Germany",
                "locationUrl": "/europe/germany",
                "locationType": "COUNTRY",
                "locationChildren": [
                    {
                        "locationName": "Berlin",
                        "locationUrl": "/europe/germany/berlin",
                        "locationType": "CITY"
                    },
                    {
                        "locationName": "Frankfurt",
                        "locationUrl": "/europe/germany/frankfurt",
                        "locationType": "CITY"
                    }
                ]
            }
        ]
    }
]
